hyde/hyde.py
hyde_generator-0.0.4.dist-info/METADATA
hyde_generator-0.0.4.dist-info/WHEEL
hyde_generator-0.0.4.dist-info/entry_points.txt
hyde_generator-0.0.4.dist-info/top_level.txt
hyde_generator-0.0.4.dist-info/RECORD
