Metadata-Version: 2.1
Name: hyde-generator
Version: 0.0.4
Summary: a simple static site generator
Home-page: https://github.com/0x44RU5H/hyde
Author: Aarush Gupta
Author-email: aarush@theaarushgupta.com
License: AGPLv3+
Platform: UNKNOWN
Classifier: License :: OSI Approved :: GNU Affero General Public License v3 or later (AGPLv3+)
Classifier: Programming Language :: Python :: 3
Classifier: Programming Language :: Python :: 3.8
Requires-Dist: Markdown
Requires-Dist: jinja2
Requires-Dist: pyyaml
